charmlibs/passwd/__init__.py
charmlibs/passwd/_passwd.py
charmlibs/passwd/_version.py
charmlibs/passwd/py.typed
charmlibs_passwd-1.0.0.dist-info/METADATA
charmlibs_passwd-1.0.0.dist-info/WHEEL
charmlibs_passwd-1.0.0.dist-info/RECORD
